django_front_end_validators-0.1.1.dist-info/METADATA
django_front_end_validators-0.1.1.dist-info/RECORD
django_front_end_validators-0.1.1.dist-info/WHEEL
django_front_end_validators-0.1.1.dist-info/top_level.txt
front_end_validators/__init__.py
front_end_validators/admin.py
front_end_validators/forms.py
front_end_validators/models.py
front_end_validators/urls.py
front_end_validators/utils.py
front_end_validators/management/__init__.py
front_end_validators/management/commands/__init__.py
front_end_validators/management/commands/transpile_validators.py
front_end_validators/static/css/front_end_validators.css
front_end_validators/static/img/.gitignore
front_end_validators/static/js/front_end_validators.js
front_end_validators/templates/front_end_validators/base.html
front_end_validators/templates/front_end_validators/script_tag_transcrypt_36.html
front_end_validators/templates/front_end_validators/script_tag_transcrypt_37.html
front_end_validators/templatetags/front_end_validators.py
