Metadata-Version: 2.1
Name: django-front-end-validators
Version: 0.1.1
Summary: Use model field validator functions for front end JS validation
Home-page: https://github.com/johnfraney/django-front-end-validators
Author: John Franey
Author-email: johnfraney@gmail.com
License: MIT
Keywords: django-front-end-validators
Platform: UNKNOWN
Classifier: Development Status :: 3 - Alpha
Classifier: Framework :: Django :: 1.11
Classifier: Framework :: Django :: 2.0
Classifier: Framework :: Django :: 2.1
Classifier: Intended Audience :: Developers
Classifier: License :: OSI Approved :: BSD License
Classifier: Natural Language :: English
Classifier: Programming Language :: Python :: 3
Classifier: Programming Language :: Python :: 3.6
Classifier: Programming Language :: Python :: 3.7
Requires-Dist: transcrypt (>=3.6)
